{
  "twitter": "https://twitter.com/zetabites",
  "instagram": "https://instagram.com/Sparkenstein_",
  "youtube": "https://youtube.com/@SparkFoss",
  "linkedin": "https://linkedin.com/in/Sparkenstein",
  "github": "https://github.com/Sparkenstein",
  "gitlab": "",
  "medium": "",
  "codepen": "",
  "bitbucket": "",
  "dribbble": "https://dribbble.com/Prabhanjan",
  "behance": "http://be.net/sparkenstein",
  "pinterest": "",
  "soundcloud": "",
  "tumblr": "",
  "reddit": "https://reddit.com/u/sparkenstein",
  "vk": "",
  "whatsapp": "",
  "snapchat": "",
  "vimeo": "",
  "tiktok": "",
  "foursquare": "",
  "rss": "",
  "email": "",
  "phone": "",
  "address": "",
  "skype": "",
  "website": "",
  "telegram": "https://t.me/Sparkenstein"
}
